frogtips/__init__.py
frogtips/__main__.py
frogtips/constants.py
frogtips/frogsay.py
frogtips/api/Credentials.py
frogtips/api/Tip.py
frogtips/api/Tips.py
frogtips/api/__init__.py
frogtips-3.0.5.dist-info/LICENSE
frogtips-3.0.5.dist-info/METADATA
frogtips-3.0.5.dist-info/WHEEL
frogtips-3.0.5.dist-info/entry_points.txt
frogtips-3.0.5.dist-info/top_level.txt
frogtips-3.0.5.dist-info/RECORD
