Metadata-Version: 2.1
Name: frogtips
Version: 3.0.5
Summary: Tips for how to operate your FROG
Home-page: https://frog.tips/
Author: FROG Systems, Inc.
Author-email: admin@frog.tips
License: MIT
Platform: UNKNOWN
Classifier: Programming Language :: Python :: 3
Classifier: License :: OSI Approved :: MIT License
Classifier: Operating System :: OS Independent
Requires-Dist: requests
